agents_bar/__init__.py
agents_bar/agents.py
agents_bar/client.py
agents_bar/environments.py
agents_bar/experiments.py
agents_bar/remote_agent.py
agents_bar/remote_env.py
agents_bar/types.py
agents_bar/utils.py
agents_bar-0.4.2.dist-info/METADATA
agents_bar-0.4.2.dist-info/WHEEL
agents_bar-0.4.2.dist-info/top_level.txt
agents_bar-0.4.2.dist-info/RECORD
