Metadata-Version: 2.1
Name: agents-bar
Version: 0.4.2
Summary: A client to work with Agents Bar (https://agents.bar).
Home-page: https://github.com/agents-bar/agents-bar-client-python
Author: Dawid Laszuk
Author-email: agents-bar-client-python@dawid.lasz.uk
License: UNKNOWN
Platform: UNKNOWN
Classifier: Programming Language :: Python :: 3
Classifier: License :: OSI Approved :: Apache Software License
Classifier: Operating System :: OS Independent
Classifier: Intended Audience :: Developers
Classifier: Intended Audience :: Science/Research
Classifier: Topic :: Scientific/Engineering :: Artificial Intelligence
Requires-Python: >=3.6
Requires-Dist: requests (~=2.25)
Requires-Dist: tenacity (~=7.0.0)
Provides-Extra: gym
Requires-Dist: gym (~=0.18.0) ; extra == 'gym'
Provides-Extra: lint
Requires-Dist: pylint (~=2.7.4) ; extra == 'lint'
